{"dependencies":[{"name":"_css_loader"}],"generated":{"css":"body {\n  display: -ms-grid;\n  display: grid;\n  margin: 0 auto;\n  padding: 0;\n  background: red;\n  color: #555; }\n  body p {\n    display: -webkit-box;\n    display: -ms-flexbox;\n    display: flex;\n    background: blue;\n    color: #fff;\n    padding: 0 50px; }\n    body p span {\n      width: 100px;\n      height: 100px;\n      background: yellow;\n      color: gray; }\n\nimg {\n  margin: 0; }\n\n.__test_ezg10_21_1is54_24 {\n  margin: 0;\n  padding: 0;\n  color: blue; }\n  .__test_ezg10_21_1is54_24 a {\n    display: -ms-grid;\n    display: grid;\n    pointer-events: none; }\n","js":"\n        var reloadCSS = require('_css_loader');\n        module.hot.dispose(reloadCSS);\n        module.hot.accept(reloadCSS);\n      module.exports = {\n  \"_test_ezg10_21\": \"__test_ezg10_21_1is54_24\"\n};"},"hash":"2c184d9660f1b9c20f12b8c1b9bff737"}